counterix
